README.md
setup.py
annotated_images/__init__.py
annotated_images/parse_tags.py
annotated_images/split.py
annotated_images.egg-info/PKG-INFO
annotated_images.egg-info/SOURCES.txt
annotated_images.egg-info/dependency_links.txt
annotated_images.egg-info/top_level.txt