Metadata-Version: 2.1
Name: annotated-images
Version: 0.1.4
Summary: Split training data images into training, validation and test (dataset) folders.
Home-page: https://github.com/saberd/annotated-images
Author: saberd
Author-email: mail@saberd.com
License: MIT
Platform: UNKNOWN
Classifier: Topic :: Scientific/Engineering :: Artificial Intelligence
Classifier: Programming Language :: Python :: 3.6
Classifier: Programming Language :: Python :: 3.7
Classifier: License :: OSI Approved :: MIT License
Classifier: Topic :: Utilities
